updrytwist/__init__.py
updrytwist/command_to_config.py
updrytwist/config.py
updrytwist/filerotator.py
updrytwist/gentleargparser.py
updrytwist/geolocate.py
updrytwist/loop_runner.py
updrytwist/mailer.py
updrytwist/mqttdriver.py
updrytwist/music-test.py
updrytwist/music.py
updrytwist/piwigo.py
updrytwist/strcompress.py
updrytwist/tkasync.py
updrytwist_UpDryTwist-0.0.42.dist-info/LICENSE
updrytwist_UpDryTwist-0.0.42.dist-info/METADATA
updrytwist_UpDryTwist-0.0.42.dist-info/WHEEL
updrytwist_UpDryTwist-0.0.42.dist-info/top_level.txt
updrytwist_UpDryTwist-0.0.42.dist-info/RECORD
