Metadata-Version: 2.1
Name: updrytwist-UpDryTwist
Version: 0.0.42
Summary: My common utilities
Home-page: https://github.com/tathamg/updrytwist
Author: Greg Tatham
Author-email: tathamg@gmail.com
Project-URL: Bug Tracker, https://github.com/tathamg/updrytwist/issues
Classifier: Programming Language :: Python :: 3
Classifier: License :: OSI Approved :: GNU General Public License v3 (GPLv3)
Classifier: Operating System :: OS Independent
Requires-Python: >=3.6
License-File: LICENSE
